{
  "json": {
    "commentLine.forceSpaceAfterSlashes": true,
    "deno": true,
    "lineWidth": 120
  },
  "markdown": {
    "deno": true,
    "lineWidth": 120
  },
  "plugins": [
    "https://plugins.dprint.dev/g-plane/pretty_yaml-v0.5.1.wasm",
    "https://plugins.dprint.dev/json-0.20.0.wasm",
    "https://plugins.dprint.dev/markdown-0.18.0.wasm",
    "https://plugins.dprint.dev/typescript-0.95.3.wasm"
  ],
  "typescript": {
    "commentLine.forceSpaceAfterSlashes": true,
    "deno": true,
    "enumDeclaration.memberSpacing": "newLine",
    "lineWidth": 120,
    "memberExpression.linePerExpression": true,
    "module.sortExportDeclarations": "caseInsensitive",
    "module.sortImportDeclarations": "caseInsensitive",
    "preferSingleLine": true,
    "quoteProps": "consistent",
    "singleBodyPosition": "sameLine"
  },
  "yaml": {
    "dashSpacing": "oneSpace",
    "formatComments": true,
    "preferSingleLine": true,
    "printWidth": 120,
    "trimTrailingZero": true
  }
}
